mrkd.py
mrkd/__init__.py
mrkd/__main__.py
mrkd/template.html
mrkd-0.2.0.dist-info/LICENSE
mrkd-0.2.0.dist-info/METADATA
mrkd-0.2.0.dist-info/WHEEL
mrkd-0.2.0.dist-info/entry_points.txt
mrkd-0.2.0.dist-info/top_level.txt
mrkd-0.2.0.dist-info/RECORD
