Metadata-Version: 2.1
Name: mrkd
Version: 0.2.0
Summary: Write man pages using Markdown, and convert them to Roff or HTML
Home-page: https://github.com/refi64/mrkd
Author: Ryan Gonzalez
Author-email: rymg19@gmail.com
License: BSD
Platform: UNKNOWN
Classifier: Programming Language :: Python :: 3 :: Only
Classifier: License :: OSI Approved :: BSD License
License-File: LICENSE
Requires-Dist: Jinja2
Requires-Dist: mistune
Requires-Dist: pygments
